janit.py
termGame.py
Janit/__init__.py
Janit/cmd/example.py
Janit/cmd/fun.py
Janit/cmd/keyboard.py
Janit/cmd/liveusb.py
Janit/cmd/man.py
Janit/cmd/nspawn.py
Janit/cmd/shell.py
Janit/cmd/watch.py
Janit/core/bash.py
Janit/core/chroot.py
Janit/core/core.py
Janit/core/display.py
Janit/core/menu.py
Janit/core/ssh.py
janit-0.0.7.dist-info/METADATA
janit-0.0.7.dist-info/WHEEL
janit-0.0.7.dist-info/entry_points.txt
janit-0.0.7.dist-info/top_level.txt
janit-0.0.7.dist-info/RECORD
