Metadata-Version: 2.1
Name: janit
Version: 0.0.7
Summary: Terminal multiplexer/Menu
Home-page: https://bitbucket.org/hackersgame/janit/src/master/
Author: David Hamner
Author-email: ke7oxh@gmail.com
License: UNKNOWN
Platform: UNKNOWN
Classifier: Programming Language :: Python :: 3.6
Requires-Dist: pyte
